lifester/__main__.py
lifester/analytics.py
lifester/category_loader.py
lifester/data_entry.py
lifester/data_from_file.py
lifester/file_loader.py
lifester/global_variables.py
lifester-1.2.0.dist-info/METADATA
lifester-1.2.0.dist-info/RECORD
lifester-1.2.0.dist-info/WHEEL
lifester-1.2.0.dist-info/entry_points.txt
lifester-1.2.0.dist-info/top_level.txt
