Metadata-Version: 2.1
Name: lifester
Version: 1.2.0
Summary: very minute of your life. On the command line.
Home-page: https://github.com/sophieau/lifester
Author: Sophie Au
Author-email: some.person@web.de
License: MIT
Keywords: command-line-tool,productivity
Platform: UNKNOWN
Requires-Python: >=3.6
Requires-Dist: tabulate (>=0.8.2)
